tox_min_req/__init__.py
tox_min_req/_parse_dependencies.py
tox_min_req/_tox_plugin.py
tox_min_req/_version.py
tox_min_req-0.0.9.dist-info/LICENSE.txt
tox_min_req-0.0.9.dist-info/METADATA
tox_min_req-0.0.9.dist-info/WHEEL
tox_min_req-0.0.9.dist-info/entry_points.txt
tox_min_req-0.0.9.dist-info/top_level.txt
tox_min_req-0.0.9.dist-info/RECORD
