Metadata-Version: 2.2
Name: tox-min-req
Version: 0.0.9
Summary: Tox plugin to run tests with minimal requirements base on setup.cfg or pyproject.toml
Author-email: Grzegorz Bokota <bokota+github@gmail.com>
License: MIT
Project-URL: Documentation, https://github.com/czaki/tox-min-req#readme
Project-URL: Issues, https://github.com/czaki/tox-min-req/issues
Project-URL: Source, https://github.com/czaki/tox-min-req
Classifier: Development Status :: 3 - Alpha
Classifier: Programming Language :: Python
Classifier: Programming Language :: Python :: 3.8
Classifier: Programming Language :: Python :: 3.9
Classifier: Programming Language :: Python :: 3.10
Classifier: Programming Language :: Python :: 3.11
Classifier: Programming Language :: Python :: 3.12
Classifier: Programming Language :: Python :: 3.13
Classifier: Programming Language :: Python :: Implementation :: CPython
Classifier: License :: OSI Approved :: MIT License
Classifier: Operating System :: OS Independent
Classifier: Topic :: Software Development :: Testing
Classifier: Intended Audience :: Developers
Classifier: Framework :: tox
Requires-Python: >=3.7
License-File: LICENSE.txt
Requires-Dist: packaging>=20.0
Requires-Dist: tox>=4.0.0
Requires-Dist: toml>=0.10.2; python_version < "3.11"
Provides-Extra: testing
Requires-Dist: pytest; extra == "testing"
Requires-Dist: tox[test]; extra == "testing"
Requires-Dist: coverage; extra == "testing"
